{
  "number": 95,
  "name": "At-Tin",
  "script": "IndoPak-Nastaleeq",
  "ayat_count": 8,
  "ayat": [
    {
      "number": 1,
      "text": "وَالتِّیْنِ وَالزَّیْتُوْنِ ۟ۙ"
    },
    {
      "number": 2,
      "text": "وَطُوْرِ سِیْنِیْنَ ۟ۙ"
    },
    {
      "number": 3,
      "text": "وَهٰذَا الْبَلَدِ الْاَمِیْنِ ۟ۙ"
    },
    {
      "number": 4,
      "text": "لَقَدْ خَلَقْنَا الْاِنْسَانَ فِیْۤ اَحْسَنِ تَقْوِیْمٍ ۟ؗ"
    },
    {
      "number": 5,
      "text": "ثُمَّ رَدَدْنٰهُ اَسْفَلَ سٰفِلِیْنَ ۟ۙ"
    },
    {
      "number": 6,
      "text": "اِلَّا الَّذِیْنَ اٰمَنُوْا وَعَمِلُوا الصّٰلِحٰتِ فَلَهُمْ اَجْرٌ غَیْرُ مَمْنُوْنٍ ۟ؕ"
    },
    {
      "number": 7,
      "text": "فَمَا یُكَذِّبُكَ بَعْدُ بِالدِّیْنِ ۟ؕ"
    },
    {
      "number": 8,
      "text": "اَلَیْسَ اللّٰهُ بِاَحْكَمِ الْحٰكِمِیْنَ ۟۠"
    }
  ],
  "source": {
    "dataset": "indopak_nastaleeq_json_uploaded",
    "version": "v1"
  }
}
