{
  "number": 104,
  "name": "Al-Humazah",
  "script": "IndoPak",
  "ayat_count": 9,
  "ayat": [
    {
      "number": 1,
      "text": "وَيۡلٌ لِّـكُلِّ هُمَزَةٍ لُّمَزَةِ ۙ‏"
    },
    {
      "number": 2,
      "text": "اۨلَّذِىۡ جَمَعَ مَالًا وَّعَدَّدَهٗ ۙ‏"
    },
    {
      "number": 3,
      "text": "يَحۡسَبُ اَنَّ مَالَهٗۤ اَخۡلَدَهٗ​ ۚ‏"
    },
    {
      "number": 4,
      "text": "كَلَّا​ لَيُنۡۢبَذَنَّ فِى الۡحُطَمَةِ  ۖ‏"
    },
    {
      "number": 5,
      "text": "وَمَاۤ اَدۡرٰٮكَ مَا الۡحُطَمَةُ ؕ‏"
    },
    {
      "number": 6,
      "text": "نَارُ اللّٰهِ الۡمُوۡقَدَةُ ۙ‏"
    },
    {
      "number": 7,
      "text": "الَّتِىۡ تَطَّلِعُ عَلَى الۡاَفۡـــِٕدَةِ ؕ‏"
    },
    {
      "number": 8,
      "text": "اِنَّهَا عَلَيۡهِمۡ مُّؤۡصَدَةٌ ۙ‏"
    },
    {
      "number": 9,
      "text": "فِىۡ عَمَدٍ مُّمَدَّدَةٍ‏"
    }
  ],
  "source": {
    "dataset": "indopak_json_uploaded",
    "version": "v1"
  }
}